.gitlab-ci.yml
.travis.yml
CHANGES.rst
CONTRIBUTORS.rst
DEVELOP.rst
LICENSE.GPL
LICENSE.rst
MANIFEST.in
README.rst
requirements.txt
setup.cfg
setup.py
docs/index.rst
src/urban/__init__.py
src/urban.restapi.egg-info/PKG-INFO
src/urban.restapi.egg-info/SOURCES.txt
src/urban.restapi.egg-info/dependency_links.txt
src/urban.restapi.egg-info/entry_points.txt
src/urban.restapi.egg-info/namespace_packages.txt
src/urban.restapi.egg-info/not-zip-safe
src/urban.restapi.egg-info/requires.txt
src/urban.restapi.egg-info/top_level.txt
src/urban/restapi/__init__.py
src/urban/restapi/configure.zcml
src/urban/restapi/exceptions.py
src/urban/restapi/interfaces.py
src/urban/restapi/permissions.zcml
src/urban/restapi/setuphandlers.py
src/urban/restapi/testing.py
src/urban/restapi/upgrades.py
src/urban/restapi/upgrades.zcml
src/urban/restapi/locales/README.rst
src/urban/restapi/locales/__init__.py
src/urban/restapi/locales/update.py
src/urban/restapi/locales/update.sh
src/urban/restapi/locales/urban.restapi.pot
src/urban/restapi/locales/en/LC_MESSAGES/urban.restapi.po
src/urban/restapi/profiles/default/browserlayer.xml
src/urban/restapi/profiles/default/catalog.xml
src/urban/restapi/profiles/default/metadata.xml
src/urban/restapi/profiles/default/registry.xml
src/urban/restapi/profiles/default/rolemap.xml
src/urban/restapi/profiles/uninstall/browserlayer.xml
src/urban/restapi/services/__init__.py
src/urban/restapi/services/configure.zcml
src/urban/restapi/services/content/__init__.py
src/urban/restapi/services/content/configure.zcml
src/urban/restapi/services/content/utils.py
src/urban/restapi/services/content/address/__init__.py
src/urban/restapi/services/content/address/base.py
src/urban/restapi/services/content/address/configure.zcml
src/urban/restapi/services/content/elements/__init__.py
src/urban/restapi/services/content/elements/base.py
src/urban/restapi/services/content/elements/configure.zcml
src/urban/restapi/services/content/esb/__init__.py
src/urban/restapi/services/content/esb/base.py
src/urban/restapi/services/content/esb/configure.zcml
src/urban/restapi/services/content/esb/envclassthree.py
src/urban/restapi/services/content/licence/__init__.py
src/urban/restapi/services/content/licence/base.py
src/urban/restapi/services/content/licence/buildlicence.py
