Metadata-Version: 2.1
Name: urban.restapi
Version: 1.0a1
Summary: specific urban restapi for interoperability
Home-page: https://pypi.python.org/pypi/urban.restapi
Author: Julien Jaumotte
Author-email: julien.jaumotte@imio.be
License: GPL version 2
Keywords: Python Plone
Platform: UNKNOWN
Classifier: Environment :: Web Environment
Classifier: Framework :: Plone
Classifier: Framework :: Plone :: 4.3
Classifier: Programming Language :: Python
Classifier: Programming Language :: Python :: 2.7
Classifier: Operating System :: OS Independent
Classifier: License :: OSI Approved :: GNU General Public License v2 (GPLv2)
Provides-Extra: test
